[
    {
        "Date": "2022-09-07",
        "Zip": "20851",
        "OrderID": 968821,
        "OrderLines": "[{\"ProductID\":2354,\"Date\":\"2022-09-07\",\"Units\":1,\"Revenue\":362.1975,\"OrderLine\":1}]"
    },
    {
        "Date": "2022-09-07",
        "Zip": "36693",
        "OrderID": 968951,
        "OrderLines": "[{\"ProductID\":1155,\"Date\":\"2022-09-07\",\"Units\":1,\"Revenue\":446.1975,\"OrderLine\":1}]"
    },
    {
        "Date": "2022-09-06",
        "Zip": "78725",
        "OrderID": 968487,
        "OrderLines": "[{\"ProductID\":1186,\"Date\":\"2022-09-06\",\"Units\":1,\"Revenue\":383.1975,\"OrderLine\":1}]"
    },
    {
        "Date": "2022-09-07",
        "Zip": "95624",
        "OrderID": 969380,
        "OrderLines": "[{\"ProductID\":2331,\"Date\":\"2022-09-07\",\"Units\":1,\"Revenue\":582.6975,\"OrderLine\":1}]"
    },
    {
        "Date": "2022-09-06",
        "Zip": "78550",
        "OrderID": 968474,
        "OrderLines": "[{\"ProductID\":2090,\"Date\":\"2022-09-06\",\"Units\":1,\"Revenue\":356.9475,\"OrderLine\":1}]"
    },
    {
        "Date": "2022-09-06",
        "Zip": "94553",
        "OrderID": 968709,
        "OrderLines": "[{\"ProductID\":777,\"Date\":\"2022-09-06\",\"Units\":1,\"Revenue\":121.7475,\"OrderLine\":1}]"
    },
    {
        "Date": "2022-09-07",
        "Zip": "64093",
        "OrderID": 969076,
        "OrderLines": "[{\"ProductID\":475,\"Date\":\"2022-09-07\",\"Units\":1,\"Revenue\":1085.9625,\"OrderLine\":1}]"
    }
]