[
    {
        "Date": "2017-03-22",
        "Zip": "32327",
        "OrderID": 78751,
        "OrderLines": "[{\"ProductID\":2188,\"Date\":\"2017-03-22\",\"Units\":1,\"Revenue\":233.5725,\"OrderLine\":1}]"
    },
    {
        "Date": "2017-03-21",
        "Zip": "78757",
        "OrderID": 78574,
        "OrderLines": "[{\"ProductID\":2352,\"Date\":\"2017-03-21\",\"Units\":1,\"Revenue\":367.4475,\"OrderLine\":1}]"
    },
    {
        "Date": "2017-03-22",
        "Zip": "37711",
        "OrderID": 78800,
        "OrderLines": "[{\"ProductID\":770,\"Date\":\"2017-03-22\",\"Units\":1,\"Revenue\":257.1975,\"OrderLine\":1}]"
    },
    {
        "Date": "2017-03-21",
        "Zip": "93927",
        "OrderID": 78647,
        "OrderLines": "[{\"ProductID\":2270,\"Date\":\"2017-03-21\",\"Units\":1,\"Revenue\":309.6975,\"OrderLine\":1}]"
    },
    {
        "Date": "2017-03-20",
        "Zip": "54639",
        "OrderID": 77984,
        "OrderLines": "[{\"ProductID\":2240,\"Date\":\"2017-03-20\",\"Units\":1,\"Revenue\":86.5725,\"OrderLine\":1}]"
    },
    {
        "Date": "2017-03-17",
        "Zip": "97202",
        "OrderID": 77720,
        "OrderLines": "[{\"ProductID\":713,\"Date\":\"2017-03-17\",\"Units\":1,\"Revenue\":162.6975,\"OrderLine\":1}]"
    }
]